llama_index/networks/__init__.py
llama_index/networks/contributor/__init__.py
llama_index/networks/contributor/query_engine/__init__.py
llama_index/networks/contributor/query_engine/client.py
llama_index/networks/contributor/query_engine/service.py
llama_index/networks/contributor/retriever/__init__.py
llama_index/networks/contributor/retriever/client.py
llama_index/networks/contributor/retriever/service.py
llama_index/networks/network/__init__.py
llama_index/networks/network/query_engine.py
llama_index/networks/network/retriever.py
llama_index/networks/schema/__init__.py
llama_index/networks/schema/contributor.py
llama_index_networks-0.6.0.dist-info/METADATA
llama_index_networks-0.6.0.dist-info/WHEEL
llama_index_networks-0.6.0.dist-info/RECORD
